CHANGES.txt
README.txt
setup.py
collective/__init__.py
collective.portlet.banners.egg-info/PKG-INFO
collective.portlet.banners.egg-info/SOURCES.txt
collective.portlet.banners.egg-info/dependency_links.txt
collective.portlet.banners.egg-info/entry_points.txt
collective.portlet.banners.egg-info/namespace_packages.txt
collective.portlet.banners.egg-info/not-zip-safe
collective.portlet.banners.egg-info/requires.txt
collective.portlet.banners.egg-info/top_level.txt
collective/portlet/__init__.py
collective/portlet/banners/__init__.py
collective/portlet/banners/bannersportlet.pt
collective/portlet/banners/bannersportlet.py
collective/portlet/banners/config.py
collective/portlet/banners/configure.zcml
collective/portlet/banners/interfaces.py
collective/portlet/banners/portletbanners.js
collective/portlet/banners/upgrades.py
collective/portlet/banners/upgrades.zcml
collective/portlet/banners/content/__init__.py
collective/portlet/banners/content/configure.zcml
collective/portlet/banners/content/portletbanner.py
collective/portlet/banners/profiles/default/browserlayer.xml
collective/portlet/banners/profiles/default/catalog.xml
collective/portlet/banners/profiles/default/factorytool.xml
collective/portlet/banners/profiles/default/jsregistry.xml
collective/portlet/banners/profiles/default/metadata.xml
collective/portlet/banners/profiles/default/portlets.xml
collective/portlet/banners/profiles/default/propertiestool.xml
collective/portlet/banners/profiles/default/types.xml
collective/portlet/banners/profiles/default/types/PortletBanner.xml
collective/portlet/banners/tests/__init__.py
collective/portlet/banners/tests/base.py
collective/portlet/banners/tests/test_portlet.py
docs/INSTALL.txt
docs/LICENSE.GPL
docs/LICENSE.txt