Metadata-Version: 1.1
Name: collective.portlet.banners
Version: 1.1
Summary: A portlet to rotate clickable banners.
Home-page: http://svn.plone.org/svn/collective/collective.portlet.banners/trunk
Author: Matt Yoder
Author-email: mattyoder@groundwire.org
License: GPL
Keywords: Plone portlet banner rotating image sponsor logo
Platform: UNKNOWN
Classifier: Framework :: Plone
Classifier: Programming Language :: Python
